directus_py_sdk/__init__.py
directus_py_sdk/exceptions.py
directus_py_sdk/main.py
directus_py_sdk-1.2.0.dist-info/licenses/LICENSE.md
directus_py_sdk-1.2.0.dist-info/METADATA
directus_py_sdk-1.2.0.dist-info/WHEEL
directus_py_sdk-1.2.0.dist-info/entry_points.txt
directus_py_sdk-1.2.0.dist-info/top_level.txt
directus_py_sdk-1.2.0.dist-info/RECORD
