Metadata-Version: 2.4
Name: directus-py-sdk
Version: 1.2.0
Summary: Python SDK for interacting with Directus API (colletion, items, users, files)
Home-page: https://github.com/Dembrane/directus-py-sdk
Author: Dembrane
Author-email: info@dembrane.com
License: MIT
Classifier: License :: OSI Approved :: MIT License
Classifier: Programming Language :: Python :: 3.7
Classifier: Programming Language :: Python :: 3.8
Classifier: Programming Language :: Python :: 3.9
Classifier: Programming Language :: Python :: 3.10
License-File: LICENSE.md
Requires-Dist: requests
Requires-Dist: urllib3
Requires-Dist: sqlparse
Dynamic: author
Dynamic: author-email
Dynamic: classifier
Dynamic: description
Dynamic: description-content-type
Dynamic: home-page
Dynamic: license
Dynamic: license-file
Dynamic: requires-dist
Dynamic: summary
